README.md
setup.cfg
setup.py
distributions_858/Binomialdistribution.py
distributions_858/Gaussiandistribution.py
distributions_858/Generaldistribution.py
distributions_858/__init__.py
distributions_858.egg-info/PKG-INFO
distributions_858.egg-info/SOURCES.txt
distributions_858.egg-info/dependency_links.txt
distributions_858.egg-info/not-zip-safe
distributions_858.egg-info/top_level.txt